CHANGES.rst
MANIFEST.in
README.md
setup.cfg
setup.py
django_admin_rq/__init__.py
django_admin_rq/admin.py
django_admin_rq/exceptions.py
django_admin_rq/models.py
django_admin_rq/serializers.py
django_admin_rq/tests.py
django_admin_rq/urls.py
django_admin_rq/views.py
django_admin_rq.egg-info/PKG-INFO
django_admin_rq.egg-info/SOURCES.txt
django_admin_rq.egg-info/dependency_links.txt
django_admin_rq.egg-info/not-zip-safe
django_admin_rq.egg-info/requires.txt
django_admin_rq.egg-info/top_level.txt
django_admin_rq/locale/.gitignore
django_admin_rq/locale/de/LC_MESSAGES/django.mo
django_admin_rq/locale/de/LC_MESSAGES/django.po
django_admin_rq/migrations/0001_initial.py
django_admin_rq/migrations/__init__.py
django_admin_rq/static/django_admin_rq/css/django_admin_rq.css
django_admin_rq/static/django_admin_rq/js/django_admin_rq.js
django_admin_rq/templates/django_admin_rq/change_form.html
django_admin_rq/templates/django_admin_rq/change_list.html
django_admin_rq/templates/django_admin_rq/job_base.html
django_admin_rq/templates/django_admin_rq/job_complete.html
django_admin_rq/templates/django_admin_rq/job_form.html
django_admin_rq/templates/django_admin_rq/job_run.html