Metadata-Version: 1.1
Name: django-admin-rq
Version: 0.1.2
Summary: Django admin rq is a django package that creates a 4 step (form, preview, main, complete) asynchronous workflow from a ModelAdmin's changelist or changeform.
Home-page: https://github.com/Proper-Job/django-admin-rq
Author: Moritz Pfeiffer
Author-email: moritz.pfeiffer@alp-phone.ch
License: MIT License
Platform: UNKNOWN
Classifier: Development Status :: 4 - Beta
Classifier: Environment :: Web Environment
Classifier: Framework :: Django
Classifier: Intended Audience :: Developers
Classifier: License :: OSI Approved :: MIT License
Classifier: Operating System :: OS Independent
Classifier: Programming Language :: Python
Classifier: Programming Language :: Python :: 3
Classifier: Topic :: Internet :: WWW/HTTP
Classifier: Topic :: Internet :: WWW/HTTP :: Dynamic Content
